Attention_Maps_Extraction/__init__.py
Attention_Maps_Extraction/dataset.py
Attention_Maps_Extraction/model.py
Attention_Maps_Extraction/utils.py
Attention_Maps_Extraction/visualize.py
Attention_Maps_Extraction-0.1.4.dist-info/METADATA
Attention_Maps_Extraction-0.1.4.dist-info/WHEEL
Attention_Maps_Extraction-0.1.4.dist-info/top_level.txt
Attention_Maps_Extraction-0.1.4.dist-info/RECORD
